{
  "hash": "34beb485",
  "configHash": "2720866d",
  "lockfileHash": "4dcad6b7",
  "browserHash": "c8a92e65",
  "optimized": {
    "react/jsx-dev-runtime": {
      "src": "../../node_modules/react/jsx-dev-runtime.js",
      "file": "react_jsx-dev-runtime.js",
      "fileHash": "6ed17d9a",
      "needsInterop": true
    },
    "react": {
      "src": "../../node_modules/react/index.js",
      "file": "react.js",
      "fileHash": "261e69cc",
      "needsInterop": true
    },
    "react-dom/client": {
      "src": "../../node_modules/react-dom/client.js",
      "file": "react-dom_client.js",
      "fileHash": "fac58941",
      "needsInterop": true
    }
  },
  "chunks": {
    "chunk-QT7PNG2D": {
      "file": "chunk-QT7PNG2D.js"
    }
  }
}